recoma/__init__.py
recoma/run_inference.py
recoma/datasets/__init__.py
recoma/datasets/bbh_reader.py
recoma/datasets/drop_reader.py
recoma/datasets/gsm8k_reader.py
recoma/datasets/reader.py
recoma/models/__init__.py
recoma/models/core/__init__.py
recoma/models/core/base_model.py
recoma/models/core/base_react_controller.py
recoma/models/core/generator.py
recoma/models/core/prompted_lm_model.py
recoma/models/core/utility_models.py
recoma/models/impl/__init__.py
recoma/models/impl/decomp_controller.py
recoma/models/impl/l2m_controller.py
recoma/models/impl/lite_llm_generator.py
recoma/models/impl/math_executer.py
recoma/models/impl/openai_generators.py
recoma/models/impl/react_controller.py
recoma/search/__init__.py
recoma/search/answerfromstate.py
recoma/search/controller.py
recoma/search/early_stopping.py
recoma/search/search.py
recoma/search/state.py
recoma/utils/class_utils.py
recoma/utils/env_utils.py
recoma/utils/state_renderer.py
recoma-0.0.5.dist-info/LICENSE
recoma-0.0.5.dist-info/METADATA
recoma-0.0.5.dist-info/WHEEL
recoma-0.0.5.dist-info/entry_points.txt
recoma-0.0.5.dist-info/top_level.txt
recoma-0.0.5.dist-info/RECORD
