Metadata-Version: 2.1
Name: recoma
Version: 0.0.5
Summary: A Python package to reason by communicating with agents
Home-page: https://github.com/allenai/recoma
Author: Tushar Khot
Author-email: tushark@allenai.org
License: UNKNOWN
Keywords: reasoning,communication,language models,tools,LLM
Platform: UNKNOWN
Classifier: Development Status :: 3 - Alpha
Classifier: Intended Audience :: Developers
Classifier: Intended Audience :: Science/Research
Classifier: Topic :: Scientific/Engineering :: Artificial Intelligence
Classifier: License :: OSI Approved :: Apache Software License
Classifier: Programming Language :: Python :: 3
Classifier: Programming Language :: Python :: 3.9
Classifier: Programming Language :: Python :: 3.10
Classifier: Programming Language :: Python :: 3.11
Classifier: Programming Language :: Python :: 3 :: Only
Requires-Python: >=3.9
Requires-Dist: treelib
Requires-Dist: jsonnet
Requires-Dist: jinja2
Requires-Dist: litellm>=1.37.19
Requires-Dist: openai>=1.47.1
Requires-Dist: diskcache
Requires-Dist: tenacity
Requires-Dist: registrable
Requires-Dist: sympy
Requires-Dist: gradio
